ca_bundle.py
ca_bundle-0.1.1.dist-info/LICENSE
ca_bundle-0.1.1.dist-info/WHEEL
ca_bundle-0.1.1.dist-info/METADATA
ca_bundle-0.1.1.dist-info/RECORD
