Metadata-Version: 2.1
Name: ca-bundle
Version: 0.1.1
Summary: No more SSL errors because of unset REQUESTS_CA_BUNDLE.
Home-page: https://github.com/matusf/ca-bundle/
License: MIT
Keywords: ssl,ca-certificates,requests
Author: Matúš Ferech
Requires-Python: >=3.6,<4.0
Classifier: License :: OSI Approved :: MIT License
Classifier: Programming Language :: Python :: 3
Classifier: Programming Language :: Python :: 3.6
Classifier: Programming Language :: Python :: 3.7
Classifier: Programming Language :: Python :: 3.8
Project-URL: Repository, https://github.com/matusf/ca-bundle/
